fanyigongju/__init__.py
fanyigongju/windows.py
fanyigongju/conf/__init__.py
fanyigongju/conf/test1.py
fanyigongju/core/__init__.py
fanyigongju/core/search.py
fanyigongju/db/__init__.py
fanyigongju/db/test2.py
fanyigongju/lib/__init__.py
fanyigongju/lib/utils.py
fanyigongju/log/__init__.py
fanyigongju-1.0.2.dist-info/AUTHORS
fanyigongju-1.0.2.dist-info/LICENSE
fanyigongju-1.0.2.dist-info/METADATA
fanyigongju-1.0.2.dist-info/WHEEL
fanyigongju-1.0.2.dist-info/top_level.txt
fanyigongju-1.0.2.dist-info/RECORD
