Metadata-Version: 2.1
Name: fanyigongju
Version: 1.0.2
Summary: 测试专用
Home-page: http://www.baidu.com
Author: ken
Author-email: xiaomishaona@126.com
Maintainer: ken
Maintainer-email: xiaomishaona@126.com
License: BSD License
Platform: all
Classifier: Development Status :: 4 - Beta
Classifier: Operating System :: OS Independent
Classifier: Intended Audience :: Developers
Classifier: License :: OSI Approved :: BSD License
Classifier: Programming Language :: Python :: 3
Classifier: Topic :: Software Development :: Libraries
Requires-Dist: certifi (>=2020.6.20)
Requires-Dist: chardet (>=3.0.4)
Requires-Dist: idna (>=2.10)
Requires-Dist: requests (>=2.24.0)
Requires-Dist: urllib3 (>=1.25.10)
